[1,["02EjQiU7ZNraMxmL2GidU0","bcJF+DKulPZJ8YQGMWKLIA@f9941","0366XSc0JB95vluoeQIJNj","1aGmMfkZFNpZWgF972rTrG@6c48a","1aGmMfkZFNpZWgF972rTrG@f9941","69qdmESeBPvYwow8ANQLlT","256V55XF9Bma0p6+//rp0X","9aCv3PguVIvoHulVT7/ves","22PY/sr7tDsK6RMXmqdvvQ","bdPFHWE/pH9YTiIDN/axXu","2dukNe5VFAjp31bWyG9FBQ","7bZ0/qfJpIWI/+Ge/fDQ+D@f9941","bcJF+DKulPZJ8YQGMWKLIA@6c48a"],["node","_spriteFrame","_font","_textureSource","_cameraComponent","audio","birdPool","pipePool","ground","tryAgainLabel","highScoreLabel","scoreLabel","readyNode","scene","_parent","audioSource","birdPrefab","prefabPipes","root","data","_defaultClip"],[["cc.Node",["_name","_layer","_id","_active","_components","_parent","_lpos","_children","_prefab","_lscale"],-1,9,1,5,2,4,5],["cc.UITransform",["node","_contentSize","_anchorPoint","__prefab"],3,1,5,5,4],["cc.Node",["_name","_layer","_parent","_components","_children","_lpos"],1,1,12,2,5],"cc.SpriteFrame",["cc.Node",["_name","_id","_parent","_components","_lpos"],1,1,2,5],["cc.Sprite",["_sizeMode","node","_spriteFrame","__prefab"],2,1,6,4],["cc.RigidBody2D",["enabledContactListener","_type","_gravityScale","_linearDamping","_fixedRotation","node","__prefab"],-2,1,4],["cc.Label",["_string","_actualFontSize","_fontSize","_lineHeight","_isSystemFontUsed","node","_font"],-2,1,6],["cc.TTFFont",["_name","_native"],1],["cc.AudioClip",["_name","_native","_duration"],0],["cc.SceneAsset",["_name"],2],["cc.Canvas",["node","_cameraComponent"],3,1,1],["cc.Widget",["_alignFlags","node"],2,1],["cc.Scene",["_name","_children","_prefab","_globals"],2,2,4,4],["cc.PrefabInfo",["root","asset","fileId","instance","targetOverrides","nestedPrefabInstanceRoots"],-3],["cc.PrefabInfo",["fileId","instance","targetOverrides","nestedPrefabInstanceRoots","root","asset"],-1,1,1],["cc.SceneGlobals",["ambient","shadows","_skybox","fog","octree","skin","lightProbeInfo"],3,4,4,4,4,4,4,4],["cc.AmbientInfo",["_skyColorHDR","_groundAlbedoHDR"],3,5,5],["cc.ShadowsInfo",["_shadowColor","_size"],3,5,5],["cc.SkyboxInfo",[],3],["cc.FogInfo",[],3],["cc.OctreeInfo",[],3],["cc.SkinInfo",["_enabled"],2],["cc.LightProbeInfo",[],3],["cc.BoxCollider2D",["node","_size"],3,1,5],["b48dfMf011Ee54JMkII2tFu",["node","readyNode","resultNode","scoreLabel","highScoreLabel","tryAgainLabel","ground","pipePool","birdPool","audio","birdPrefab"],3,1,1,1,1,1,1,1,1,1,1,6],["cc.Camera",["_projection","_orthoHeight","_near","_visibility","node","_color"],-1,1,5],["28d89zON5FPFqhD3KyorP8l",["node","ground1","ground2","ground3"],3,1,1,1,1],["a0c50cHVU1DnJ1vGIdhZH8s",["node"],3,1],["0380b2NOmtLpZBjFAEEZCnC",["clips"],3,3],["cc.AudioSource",["_volume"],2],["cc.Prefab",["_name"],2],["cc.CompPrefabInfo",["fileId"],2],["22ceeyIZ61MSZbJxOVdHYpU",["node","__prefab"],3,1,4],["cc.Animation",["node","__prefab","_clips","_defaultClip"],3,1,4,3,6],["cc.CircleCollider2D",["_radius","node","__prefab"],2,1,4]],[[1,0,1,1],[32,0,2],[9,0,1,2,4],[0,0,1,5,4,6,3],[5,0,1,2,2],[0,0,1,5,4,3],[2,0,2,3,5,2],[1,0,1,2,1],[7,0,1,2,3,4,5,6],[4,0,1,2,3,3],[6,0,1,5,3],[24,0,1,1],[8,0,1,3],[10,0,2],[0,0,1,2,7,4,6,4],[0,0,3,5,7,3],[0,0,2,5,4,6,3],[0,0,5,7,2],[0,0,5,4,6,2],[0,0,1,4,8,9,3],[2,0,1,2,4,3,3],[2,0,1,2,3,3],[4,0,2,3,4,2],[1,0,1],[1,0,3,1,1],[11,0,1,1],[12,0,1,2],[13,0,1,2,3,2],[14,0,1,2,3,4,5,7],[15,0,1,2,3,4,5,5],[16,0,1,2,3,4,5,6,1],[17,0,1,1],[18,0,1,1],[19,1],[20,1],[21,1],[22,0,2],[23,1],[5,1,3,2,1],[6,0,2,3,4,5,6,5],[25,0,1,2,3,4,5,6,7,8,9,10,1],[7,0,1,2,3,4,5,6,6],[26,0,1,2,3,4,5,5],[27,0,1,2,3,1],[28,0,1],[29,0,1],[30,0,2],[31,0,2],[33,0,1,1],[34,0,1,2,3,1],[35,0,1,2,2]],[[[[12,"FlappyBirdRegular-9Pq0","FlappyBirdRegular-9Pq0.ttf"],-1],0,0,[],[],[]],[[{"name":"background","rect":{"x":0,"y":0,"width":288,"height":512},"offset":{"x":0,"y":0},"originalSize":{"width":288,"height":512},"rotated":false,"capInsets":[0,0,0,0],"vertices":{"rawPosition":[-144,-256,0,144,-256,0,-144,256,0,144,256,0],"indexes":[0,1,2,2,1,3],"uv":[0,512,288,512,0,0,288,0],"nuv":[0,0,1,0,0,1,1,1],"minPos":{"x":-144,"y":-256,"z":0},"maxPos":{"x":144,"y":256,"z":0}},"packable":true,"pixelsToUnit":100,"pivot":{"x":0.5,"y":0.5},"meshType":0}],[3],0,[0],[3],[3]],[[[2,"hit",".wav",0.54712],-1],0,0,[],[],[]],[[[2,"wing",".wav",0.338141],-1],0,0,[],[],[]],[[[13,"main"],[14,"Canvas",33554432,"beI88Z2HpFELqR4T5EMHpg",[-5,-6,-7,-8,-9,-10,-11],[[0,-1,[5,640,960]],[25,-3,-2],[26,45,-4]],[1,320,480,0]],[20,"Ground",33554432,1,[-14,-15,-16,-17,-18],[[[0,-12,[5,0,0]],-13],4,1]],[27,"main",[-19,-20,-21,1],[28,null,null,"420dd9e5-9c96-4cac-9d46-83bc8e4da9a7",null,null,null],[30,[31,[2,0,0,0,0.520833125],[2,0,0,0,0]],[32,[4,4283190348],[0,512,512]],[33],[34],[35],[36,false],[37]]],[15,"Result",false,1,[-22,-23,-24]],[5,"Ground1",33554432,2,[[7,-25,[5,322,112],[0,1,4.5]],[4,0,-26,1]]],[3,"Ground2",33554432,2,[[7,-27,[5,322,112],[0,1,4.5]],[4,0,-28,2]],[1,320,0,0]],[3,"Ground3",33554432,2,[[7,-29,[5,322,112],[0,1,4.5]],[4,0,-30,3]],[1,640,0,0]],[3,"GroundCollider",33554432,2,[[0,-31,[5,0,0]],[10,true,0,-32],[11,-33,[5,640,100]]],[1,0,-443.398,0]],[3,"SkyCollider",33554432,2,[[0,-34,[5,0,0]],[10,true,0,-35],[11,-36,[5,640,100]]],[1,0,530,0]],[16,"GameCtrl","efMb3bn0RPAogm884SkBWu",3,[[0,-37,[5,640,960]],[40,-46,-45,4,-44,-43,-42,-41,-40,-39,-38,5]],[1,320,480,0]],[17,"Ready",1,[-47]],[5,"Background",33554432,1,[[0,-48,[5,640,960]],[4,0,-49,0]]],[21,"PipePool",33554432,1,[[[23,-50],-51],4,1]],[5,"BirdPool",33554432,1,[[0,-52,[5,0,0]]]],[6,"Score",4,[[[0,-53,[5,27.5,100.8]],-54],4,1],[1,0,150,0]],[6,"HighScore",4,[[[0,-55,[5,279.140625,75.6]],-56],4,1],[1,0,100,0]],[6,"TryAgain",4,[[[0,-57,[5,202.3828125,75.6]],-58],4,1],[1,0,-80,0]],[18,"TabToStart",11,[[0,-59,[5,269.765625,75.6]],[41,"Tab to Start!",60,60,60,false,-60,4]],[1,0,150,0]],[22,"Camera",1,[-61],[1,0,0,1000]],[42,0,480,0,1108344832,19,[4,4278190080]],[43,2,5,6,7],[44,13],[8,"0",80,80,80,false,15],[8,"High Score: 0",60,60,60,false,16],[8,"Try Again?",60,60,60,false,17],[45,[6,7,8,9]],[9,"AudioCtrl","a4okH2soROuJl+//k7ubd3",3,[26]],[46,0.5],[9,"AudioSrc","46UHv57v9Kq4ubBEHeFXFr",3,[28]]],0,[0,0,1,0,4,20,0,0,1,0,0,1,0,-1,19,0,-2,12,0,-3,2,0,-4,13,0,-5,14,0,-6,11,0,-7,4,0,0,2,0,-2,21,0,-1,5,0,-2,6,0,-3,7,0,-4,8,0,-5,9,0,-1,10,0,-2,27,0,-3,29,0,-1,15,0,-2,16,0,-3,17,0,0,5,0,0,5,0,0,6,0,0,6,0,0,7,0,0,7,0,0,8,0,0,8,0,0,8,0,0,9,0,0,9,0,0,9,0,0,10,0,5,26,0,6,14,0,7,22,0,8,21,0,9,25,0,10,24,0,11,23,0,12,11,0,0,10,0,-1,18,0,0,12,0,0,12,0,0,13,0,-2,22,0,0,14,0,0,15,0,-2,23,0,0,16,0,-2,24,0,0,17,0,-2,25,0,0,18,0,0,18,0,-1,20,0,13,3,1,14,3,26,15,28,26,0,27,28,0,29,61],[0,0,0,0,0,0,0,0,0,0,22,23,24,25],[1,1,1,1,2,16,-1,-2,-3,-4,17,2,2,2],[4,1,1,1,0,5,6,7,8,9,10,0,0,0]],[[[47,"Bird"],[19,"Bird",33554432,[[24,-2,[1,"15e3tpnnZP2J7YvNoR0DRi"],[5,34,24]],[38,-3,[1,"aeyCUrOW9L0pA1ulIXx7Lb"],0],[48,-4,[1,"31ANoTtrhDAYmW7vgTmixh"]],[49,-5,[1,"16K/rXyFJPSJUU4ph6Bq0g"],[1],2],[39,true,2.3,2,true,-6,[1,"2bpkuTPspCcqaEoAsmgEOV"]],[50,13.4,-7,[1,"23qOqkry1Dt6t1Eh5EXN9k"]]],[29,"b6deFqwRxPl78Suf3SrWbw",null,null,null,-1,0],[1,2,2,1]]],0,[0,18,1,0,0,1,0,0,1,0,0,1,0,0,1,0,0,1,0,0,1,0,19,1,7],[0,0,0],[1,-1,20],[11,2,2]],[[[2,"point",".wav",1.005714],-1],0,0,[],[],[]],[[{"name":"ground","rect":{"x":0,"y":0,"width":336,"height":112},"offset":{"x":0,"y":0},"originalSize":{"width":336,"height":112},"rotated":false,"capInsets":[0,0,0,0],"vertices":{"rawPosition":[-168,-56,0,168,-56,0,-168,56,0,168,56,0],"indexes":[0,1,2,2,1,3],"uv":[0,112,336,112,0,0,336,0],"nuv":[0,0,1,0,0,1,1,1],"minPos":{"x":-168,"y":-56,"z":0},"maxPos":{"x":168,"y":56,"z":0}},"packable":true,"pixelsToUnit":100,"pivot":{"x":0.5,"y":0.5},"meshType":0}],[3],0,[0],[3],[12]],[[[2,"die",".wav",1.104399],-1],0,0,[],[],[]]]]
